pysurveytools-0.1.0.dist-info/licenses/LICENSE
surveytools/__init__.py
surveytools/angle.py
surveytools/coordinate.py
surveytools/full_angle_measurement.py
surveytools/instrument_station.py
surveytools/measurement.py
surveytools/measurement_target.py
surveytools/surveytools.py
pysurveytools-0.1.0.dist-info/METADATA
pysurveytools-0.1.0.dist-info/WHEEL
pysurveytools-0.1.0.dist-info/entry_points.txt
pysurveytools-0.1.0.dist-info/top_level.txt
pysurveytools-0.1.0.dist-info/RECORD
